libwannier90.cpython-311-darwin.so
libwannier90-0.2.1.dist-info/LICENSE
libwannier90-0.2.1.dist-info/METADATA
libwannier90-0.2.1.dist-info/WHEEL
libwannier90-0.2.1.dist-info/top_level.txt
libwannier90-0.2.1.dist-info/RECORD
